django_ddd/__init__.py
django_ddd/apps.py
django_ddd/_app_template/__init__.py
django_ddd/_app_template/application/__init__.py
django_ddd/_app_template/domain/__init__.py
django_ddd/_app_template/infrastructure/__init__.py
django_ddd/_app_template/infrastructure/admin.py-tpl
django_ddd/_app_template/infrastructure/apps.py-tpl
django_ddd/_app_template/infrastructure/models.py-tpl
django_ddd/_app_template/infrastructure/migrations/__init__.py
django_ddd/apps_config/__init__.py
django_ddd/apps_config/clean_app_config.py
django_ddd/management/__init__.py
django_ddd/management/commands/__init__.py
django_ddd/management/commands/start_clean_app.py
Django_ddd-0.1.11.dist-info/LICENSE
Django_ddd-0.1.11.dist-info/METADATA
Django_ddd-0.1.11.dist-info/WHEEL
Django_ddd-0.1.11.dist-info/top_level.txt
Django_ddd-0.1.11.dist-info/RECORD
